azure/mgmt/scvmm/__init__.py
azure/mgmt/scvmm/_configuration.py
azure/mgmt/scvmm/_patch.py
azure/mgmt/scvmm/_sc_vmm_mgmt_client.py
azure/mgmt/scvmm/_serialization.py
azure/mgmt/scvmm/_vendor.py
azure/mgmt/scvmm/_version.py
azure/mgmt/scvmm/py.typed
azure/mgmt/scvmm/aio/__init__.py
azure/mgmt/scvmm/aio/_configuration.py
azure/mgmt/scvmm/aio/_patch.py
azure/mgmt/scvmm/aio/_sc_vmm_mgmt_client.py
azure/mgmt/scvmm/aio/operations/__init__.py
azure/mgmt/scvmm/aio/operations/_availability_sets_operations.py
azure/mgmt/scvmm/aio/operations/_clouds_operations.py
azure/mgmt/scvmm/aio/operations/_guest_agents_operations.py
azure/mgmt/scvmm/aio/operations/_inventory_items_operations.py
azure/mgmt/scvmm/aio/operations/_operations.py
azure/mgmt/scvmm/aio/operations/_patch.py
azure/mgmt/scvmm/aio/operations/_virtual_machine_instances_operations.py
azure/mgmt/scvmm/aio/operations/_virtual_machine_templates_operations.py
azure/mgmt/scvmm/aio/operations/_virtual_networks_operations.py
azure/mgmt/scvmm/aio/operations/_vm_instance_hybrid_identity_metadatas_operations.py
azure/mgmt/scvmm/aio/operations/_vmm_servers_operations.py
azure/mgmt/scvmm/models/__init__.py
azure/mgmt/scvmm/models/_models_py3.py
azure/mgmt/scvmm/models/_patch.py
azure/mgmt/scvmm/models/_sc_vmm_mgmt_client_enums.py
azure/mgmt/scvmm/operations/__init__.py
azure/mgmt/scvmm/operations/_availability_sets_operations.py
azure/mgmt/scvmm/operations/_clouds_operations.py
azure/mgmt/scvmm/operations/_guest_agents_operations.py
azure/mgmt/scvmm/operations/_inventory_items_operations.py
azure/mgmt/scvmm/operations/_operations.py
azure/mgmt/scvmm/operations/_patch.py
azure/mgmt/scvmm/operations/_virtual_machine_instances_operations.py
azure/mgmt/scvmm/operations/_virtual_machine_templates_operations.py
azure/mgmt/scvmm/operations/_virtual_networks_operations.py
azure/mgmt/scvmm/operations/_vm_instance_hybrid_identity_metadatas_operations.py
azure/mgmt/scvmm/operations/_vmm_servers_operations.py
azure_mgmt_scvmm-1.0.0.dist-info/LICENSE
azure_mgmt_scvmm-1.0.0.dist-info/METADATA
azure_mgmt_scvmm-1.0.0.dist-info/WHEEL
azure_mgmt_scvmm-1.0.0.dist-info/top_level.txt
azure_mgmt_scvmm-1.0.0.dist-info/RECORD
